cltl/combot/__init__.py
cltl/combot/event/__init__.py
cltl/combot/event/bdi.py
cltl/combot/event/emissor.py
cltl/combot/infra/__init__.py
cltl/combot/infra/di_container.py
cltl/combot/infra/docker.py
cltl/combot/infra/event_log.py
cltl/combot/infra/groupby_processor.py
cltl/combot/infra/time_util.py
cltl/combot/infra/topic_worker.py
cltl/combot/infra/util.py
cltl/combot/infra/config/__init__.py
cltl/combot/infra/config/api.py
cltl/combot/infra/config/k8config.py
cltl/combot/infra/config/local.py
cltl/combot/infra/event/__init__.py
cltl/combot/infra/event/api.py
cltl/combot/infra/event/kombu.py
cltl/combot/infra/event/memory.py
cltl/combot/infra/event/serialization.py
cltl/combot/infra/event/util.py
cltl/combot/infra/resource/__init__.py
cltl/combot/infra/resource/api.py
cltl/combot/infra/resource/threaded.py
cltl/combot/test/__init__.py
cltl/combot/test/util.py
cltl/commons/__init__.py
cltl/commons/casefolding.py
cltl/commons/discrete.py
cltl/commons/language_helpers.py
cltl/commons/triple_helpers.py
cltl/commons/language_data/__init__.py
cltl/commons/language_data/animations.py
cltl/commons/language_data/base_cases.py
cltl/commons/language_data/cfg.txt
cltl/commons/language_data/lexicon.json
cltl/commons/language_data/sentences.py
cltl.combot-1.1.0.data/data/VERSION/VERSION
cltl_service/combot/__init__.py
cltl_service/combot/event_log/__init__.py
cltl_service/combot/event_log/service.py
cltl.combot-1.1.0.dist-info/LICENCE
cltl.combot-1.1.0.dist-info/METADATA
cltl.combot-1.1.0.dist-info/WHEEL
cltl.combot-1.1.0.dist-info/top_level.txt
cltl.combot-1.1.0.dist-info/RECORD
