Metadata-Version: 2.1
Name: cltl.combot
Version: 1.1.0
Summary: Communication Robot Framework
Home-page: https://github.com/leolani/cltl-combot
Author: CLTL
Author-email: t.baier@vu.nl
License: MIT License
Requires-Python: >=3.7
License-File: LICENCE
Requires-Dist: emissor
Provides-Extra: external
Requires-Dist: kombu ; extra == 'external'
